povtas/__init__.py
povtas/main.py
povtas-0.1.10.dist-info/LICENSE
povtas-0.1.10.dist-info/METADATA
povtas-0.1.10.dist-info/WHEEL
povtas-0.1.10.dist-info/top_level.txt
povtas-0.1.10.dist-info/RECORD
