Metadata-Version: 2.1
Name: povtas
Version: 0.1.10
Summary: Turns every r of a word in a v
Author-email: totoLab <antoniolabate19@gmail.com>
License: GNU GENERAL PUBLIC LICENSE
Project-URL: Bug Tracker, https://github.com/totolab/povtas/issues
Classifier: Programming Language :: Python :: 3
Classifier: License :: OSI Approved :: MIT License
Classifier: Operating System :: OS Independent
Requires-Python: >=3.7
License-File: LICENSE
